README.txt
setup.cfg
setup.py
plone/__init__.py
plone.oofill.egg-info/PKG-INFO
plone.oofill.egg-info/SOURCES.txt
plone.oofill.egg-info/dependency_links.txt
plone.oofill.egg-info/entry_points.txt
plone.oofill.egg-info/namespace_packages.txt
plone.oofill.egg-info/not-zip-safe
plone.oofill.egg-info/requires.txt
plone.oofill.egg-info/top_level.txt
plone/oofill/__init__.py
plone/oofill/interfaces.py
plone/oofill/oofillengine.py
plone/oofill/tests.py