Metadata-Version: 1.0
Name: plone.oofill
Version: 1.0
Summary: Uses the oofill python module to fill an odt document with data.
Home-page: https://svn.plonegov.org/plone.oofill
Author: atReal
Author-email: contact@atreal.net
License: GPL
Keywords: OpenOffice odf odt
Platform: UNKNOWN
Classifier: Framework :: Plone
Classifier: Framework :: Zope2
Classifier: Framework :: Zope3
Classifier: Programming Language :: Python
Classifier: Topic :: Software Development :: Libraries :: Python Modules
